AUTHORS.rst
LICENSE
MANIFEST.in
README.rst
setup.cfg
setup.py
docs/Makefile
docs/authors.rst
docs/conf.py
docs/index.rst
docs/installation.rst
docs/make.bat
docs/modules.rst
docs/pydisp.rst
docs/readme.rst
docs/usage.rst
pydisp/__init__.py
pydisp/pydisp.py
pydisp.egg-info/PKG-INFO
pydisp.egg-info/SOURCES.txt
pydisp.egg-info/dependency_links.txt
pydisp.egg-info/not-zip-safe
pydisp.egg-info/requires.txt
pydisp.egg-info/top_level.txt
scripts/disp
tests/__init__.py
tests/test_pydisp.py