Metadata-Version: 1.1
Name: pydisp
Version: 0.0.1
Summary: python client for display
Home-page: https://github.com/dimatura/pydisp
Author: Daniel Maturana
Author-email: dimatura@cmu.edu
License: BSD
Keywords: pydisp
Platform: UNKNOWN
Classifier: Development Status :: 2 - Pre-Alpha
Classifier: Intended Audience :: Developers
Classifier: License :: OSI Approved :: BSD License
Classifier: Natural Language :: English
Classifier: Programming Language :: Python :: 2
Classifier: Programming Language :: Python :: 2.6
Classifier: Programming Language :: Python :: 2.7
Classifier: Programming Language :: Python :: 3
Classifier: Programming Language :: Python :: 3.3
Classifier: Programming Language :: Python :: 3.4
